tuxrun/__init__.py
tuxrun/__main__.py
tuxrun/argparse.py
tuxrun/assets.py
tuxrun/exceptions.py
tuxrun/requests.py
tuxrun/results.py
tuxrun/runtimes.py
tuxrun/utils.py
tuxrun/writer.py
tuxrun/xdg.py
tuxrun/yaml.py
tuxrun/templates/__init__.py
tuxrun/templates/dispatchers/dispatcher.yaml.jinja2
tuxrun/templates/wrappers/docker.jinja2
tuxrun/templates/wrappers/host-qemu.jinja2
tuxrun-1.3.2.dist-info/entry_points.txt
tuxrun-1.3.2.dist-info/licenses/LICENSE
tuxrun-1.3.2.dist-info/WHEEL
tuxrun-1.3.2.dist-info/METADATA
tuxrun-1.3.2.dist-info/RECORD
