Metadata-Version: 2.4
Name: tuxrun
Version: 1.3.2
Summary: Command line tool for testing Linux under QEMU
Home-page: https://tuxsuite.com/
Author: Antonio Terceiro
Author-email: antonio.terceiro@linaro.org
Requires-Python: >=3.6
Classifier: License :: OSI Approved :: MIT License
License-File: LICENSE
Requires-Dist: jinja2
Requires-Dist: requests
Requires-Dist: PyYAML
Requires-Dist: ruamel.yaml
Requires-Dist: tuxlava
